{
  "$schema": "https://mintlify.com/schema.json",
  "name": "Dino Corp",
  "logo": {
    "dark": "/logo/dark.svg",
    "light": "/logo/light.svg",
    "href": "https://www.liverpoolfc.com/"
  },
  "favicon": "/favicon.svg",
  "theme": "prism",
  "layout": "solidSidenav",
  "backgroundImage": "",
  "sidebar": {
    "items": "container"
  },
  "topbar": {
    "style": "default"
  },
  "search": {
    "location": "top"
  },
  "rounded": "default",
  "codeBlock": {
    "mode": "dark"
  },
  "font": {
    "headings": {
      "family": ""
    },
    "body": {
      "family": ""
    }
  },
  "background": {
    "style": "windows"
  },
  "colors": {
    "primary": "#D00027",
    "light": "#FDF667",
    "dark": "#00A398",
    "background": {
      "light": "#FFD0D0",
      "dark": "#262626"
    },
    "anchors": {
      "from": "#D00027",
      "to": "#FDF667"
    }
  },
  "topbarLinks": [
    {
      "name": "Support",
      "url": "mailto:hi@mintlify.com"
    }
  ],
  "topbarCtaButton": {
    "name": "Dashboard",
    "url": "https://dashboard.mintlify.com"
  },
  "tabs": [
    {
      "name": "API Reference",
      "url": "api-reference"
    }
  ],
  "anchors": [
    {
      "name": "Documentation",
      "icon": "book-open-cover",
      "url": "https://mintlify.com/docs"
    },
    {
      "name": "Community",
      "icon": "slack",
      "url": "https://mintlify.com/community"
    },
    {
      "name": "Blog",
      "icon": "newspaper",
      "url": "https://mintlify.com/blog"
    }
  ],
  "navigation": [
    {
      "group": "Get Started",
      "pages": [
        "introduction",
        "quickstart",
        "development"
      ]
    },
    {
      "group": "Essentials",
      "pages": [
        "essentials/markdown",
        "essentials/code",
        "essentials/images",
        "essentials/settings",
        "essentials/navigation",
        "essentials/reusable-snippets"
      ]
    },
    {
      "group": "API Documentation",
      "pages": [
        "api-reference/introduction"
      ]
    },
    {
      "group": "Endpoint Examples",
      "pages": [
        "api-reference/endpoint/get",
        "api-reference/endpoint/create",
        "api-reference/endpoint/delete"
      ]
    }
  ],
  "footerSocials": {
    "x": "https://x.com/mintlify",
    "github": "https://github.com/mintlify",
    "linkedin": "https://www.linkedin.com/company/mintsearch"
  }
}